README.md
package_info.json
setup.py
th2_grpc_books_validation/BookService.proto
th2_grpc_books_validation/BookService_pb2.py
th2_grpc_books_validation/BookService_pb2.pyi
th2_grpc_books_validation/BookService_pb2_grpc.py
th2_grpc_books_validation/__init__.py
th2_grpc_books_validation/book_service_service.py
th2_grpc_books_validation/py.typed
th2_grpc_books_validation.egg-info/PKG-INFO
th2_grpc_books_validation.egg-info/SOURCES.txt
th2_grpc_books_validation.egg-info/dependency_links.txt
th2_grpc_books_validation.egg-info/requires.txt
th2_grpc_books_validation.egg-info/top_level.txt