Metadata-Version: 2.1
Name: th2-grpc-books-validation
Version: 0.0.1
Summary: th2_grpc_books_validation
Home-page: https://github.com/th2-net/th2-grpc-books-validation.git
Author: TH2-devs
Author-email: th2-devs@exactprosystems.com
License: Apache License 2.0
Platform: UNKNOWN
Requires-Python: >=3.7
